pre_commit_cairo/__init__.py
pre_commit_cairo/check_format.py
pre_commit_cairo/check_lint.py
pre_commit_cairo-0.0.15.dist-info/entry_points.txt
pre_commit_cairo-0.0.15.dist-info/LICENSE
pre_commit_cairo-0.0.15.dist-info/WHEEL
pre_commit_cairo-0.0.15.dist-info/METADATA
pre_commit_cairo-0.0.15.dist-info/RECORD
