Metadata-Version: 2.1
Name: pre-commit-cairo
Version: 0.0.15
Summary: 
Author: franalgaba
Author-email: f.algaba@outlook.es
Requires-Python: >=3.7,<4.0
Classifier: Programming Language :: Python :: 3
Classifier: Programming Language :: Python :: 3.10
Classifier: Programming Language :: Python :: 3.7
Classifier: Programming Language :: Python :: 3.8
Classifier: Programming Language :: Python :: 3.9
Requires-Dist: cairo-lang (==0.8.1)
Requires-Dist: rich (>=12.2.0,<13.0.0)
